fstring_inspector/__init__.py
fstring_inspector/main.py
fstring_inspector-0.2.0.dist-info/LICENSE
fstring_inspector-0.2.0.dist-info/METADATA
fstring_inspector-0.2.0.dist-info/WHEEL
fstring_inspector-0.2.0.dist-info/top_level.txt
fstring_inspector-0.2.0.dist-info/RECORD
